rhme/__init__.py
rhme/api.py
rhme/config.py
rhme/example.py
rhme/recognize.py
rhme/visualizar_imagens.py
rhme/docs/config/config.json
rhme/docs/config/config_all.json
rhme/helpers/DataStructures.py
rhme/helpers/__init__.py
rhme/helpers/exceptions.py
rhme/hme_parser/__init__.py
rhme/hme_parser/check_grammar.py
rhme/hme_parser/check_grammar_lex.py
rhme/hme_parser/check_grammar_yacc.py
rhme/hme_parser/correct_grammar.py
rhme/hme_parser/parser.py
rhme/hme_parser/structural_analysis.py
rhme/hme_parser/grammar/__init__.py
rhme/hme_parser/grammar/lex.py
rhme/hme_parser/grammar/parsetab.py
rhme/hme_parser/grammar/yacc.py
rhme/images/validacao/1.png
rhme/images/validacao/10.png
rhme/images/validacao/11.png
rhme/images/validacao/12.png
rhme/images/validacao/13.png
rhme/images/validacao/14.png
rhme/images/validacao/15.png
rhme/images/validacao/16.png
rhme/images/validacao/17.png
rhme/images/validacao/18.png
rhme/images/validacao/19.png
rhme/images/validacao/2.png
rhme/images/validacao/20.png
rhme/images/validacao/21.png
rhme/images/validacao/22.png
rhme/images/validacao/23.png
rhme/images/validacao/24.png
rhme/images/validacao/25.png
rhme/images/validacao/26.png
rhme/images/validacao/27.png
rhme/images/validacao/28.png
rhme/images/validacao/29.png
rhme/images/validacao/3.png
rhme/images/validacao/30.png
rhme/images/validacao/31.png
rhme/images/validacao/32.png
rhme/images/validacao/33.png
rhme/images/validacao/34.png
rhme/images/validacao/35.png
rhme/images/validacao/36.png
rhme/images/validacao/37.png
rhme/images/validacao/39.png
rhme/images/validacao/4.png
rhme/images/validacao/40.png
rhme/images/validacao/41.png
rhme/images/validacao/42.png
rhme/images/validacao/43.png
rhme/images/validacao/44.png
rhme/images/validacao/46.png
rhme/images/validacao/47.png
rhme/images/validacao/48.png
rhme/images/validacao/49.png
rhme/images/validacao/5.png
rhme/images/validacao/50.png
rhme/images/validacao/51.png
rhme/images/validacao/52.png
rhme/images/validacao/53.png
rhme-0.5812.dist-info/METADATA
rhme-0.5812.dist-info/WHEEL
rhme-0.5812.dist-info/top_level.txt
rhme-0.5812.dist-info/RECORD
