Metadata-Version: 2.1
Name: rhme
Version: 0.5812
Summary: UNKNOWN
Home-page: https://github.com/carolreis/handwritten-mathematical-expressions-recognition
Author: Caroline Reis
Author-email: caroline.sreis@ulbra.edu.br
License: UNKNOWN
Platform: UNKNOWN
Requires-Python: >=3.6
Requires-Dist: idx2numpy
Requires-Dist: imageio
Requires-Dist: imutils
Requires-Dist: matplotlib
Requires-Dist: numpy
Requires-Dist: tensorflow
Requires-Dist: bison
Requires-Dist: ply
Requires-Dist: opencv-python
Requires-Dist: h5py
Requires-Dist: Markdown
Requires-Dist: Pillow
Requires-Dist: tensorflow (==2.2.0)
Requires-Dist: tensorflow-estimator (==2.2.0)
